README.md
setup.py
segbook/__init__.py
segbook/predict.py
segbook/segbook.py
segbook/utils.py
segbook.egg-info/PKG-INFO
segbook.egg-info/SOURCES.txt
segbook.egg-info/dependency_links.txt
segbook.egg-info/entry_points.txt
segbook.egg-info/requires.txt
segbook.egg-info/top_level.txt
segbook/nnunet/__init__.py
segbook/nnunet/configuration.py
segbook/nnunet/paths.py
segbook/nnunet/evaluation/__init__.py
segbook/nnunet/evaluation/add_dummy_task_with_mean_over_all_tasks.py
segbook/nnunet/evaluation/add_mean_dice_to_json.py
segbook/nnunet/evaluation/collect_results_files.py
segbook/nnunet/evaluation/evaluator.py
segbook/nnunet/evaluation/metrics.py
segbook/nnunet/evaluation/region_based_evaluation.py
segbook/nnunet/evaluation/surface_dice.py
segbook/nnunet/inference/__init__.py
segbook/nnunet/inference/change_trainer.py
segbook/nnunet/inference/ensemble_predictions.py
segbook/nnunet/inference/predict.py
segbook/nnunet/inference/predict_simple.py
segbook/nnunet/inference/segmentation_export.py
segbook/nnunet/inference/amos2022/__init__.py
segbook/nnunet/inference/amos2022/inference_code.py
segbook/nnunet/inference/pretrained_models/__init__.py
segbook/nnunet/inference/pretrained_models/collect_pretrained_models.py
segbook/nnunet/inference/pretrained_models/download_pretrained_model.py
segbook/nnunet/network_architecture/STUNet.py
segbook/nnunet/network_architecture/__init__.py
segbook/nnunet/network_architecture/generic_UNet.py
segbook/nnunet/network_architecture/initialization.py
segbook/nnunet/network_architecture/neural_network.py
segbook/nnunet/postprocessing/__init__.py
segbook/nnunet/postprocessing/connected_components.py
segbook/nnunet/preprocessing/__init__.py
segbook/nnunet/preprocessing/cropping.py
segbook/nnunet/preprocessing/preprocessing.py
segbook/nnunet/training/__init__.py
segbook/nnunet/training/model_restore.py
segbook/nnunet/training/cascade_stuff/__init__.py
segbook/nnunet/training/cascade_stuff/predict_next_stage.py
segbook/nnunet/training/data_augmentation/__init__.py
segbook/nnunet/training/data_augmentation/custom_transforms.py
segbook/nnunet/training/data_augmentation/data_augmentation_moreDA.py
